{
    "14166": {
        "target_position": -0.5,
        "rotated_mean_x": 0.0411827333866048,
        "rotated_mean_y": -0.016756598130452483,
        "rotated_sigma_x": 0.22386347843341725,
        "rotated_sigma_y": 0.04569594004942895,
        "rotation_angle_mrad": -0.007240105567189255
    },
    "14170": {
        "target_position": -0.5,
        "rotated_mean_x": 0.025323523452656756,
        "rotated_mean_y": 0.026054582200316034,
        "rotated_sigma_x": 0.23803808258124842,
        "rotated_sigma_y": 0.048729798022247445,
        "rotation_angle_mrad": -0.0036695686106346763
    },
    "14176": {
        "target_position": -0.5,
        "rotated_mean_x": 0.05037531503432828,
        "rotated_mean_y": -0.015359565935356145,
        "rotated_sigma_x": 0.25936694926524545,
        "rotated_sigma_y": 0.05171106385675452,
        "rotation_angle_mrad": -0.0035989252732778073
    },
    "14177": {
        "target_position": -0.5,
        "rotated_mean_x": 0.04034948683418491,
        "rotated_mean_y": -0.0015700514754320763,
        "rotated_sigma_x": 0.2531786050160827,
        "rotated_sigma_y": 0.05023181173168914,
        "rotation_angle_mrad": -0.0012723137170579624
    },
    "14180": {
        "target_position": -0.5,
        "rotated_mean_x": 0.043361450289536516,
        "rotated_mean_y": 0.013205893052469941,
        "rotated_sigma_x": 0.25070019514347186,
        "rotated_sigma_y": 0.0470913628419393,
        "rotation_angle_mrad": -0.002871998550059991
    },
    "14184": {
        "target_position": -0.5,
        "rotated_mean_x": 0.028192068019347177,
        "rotated_mean_y": 0.03324586759388238,
        "rotated_sigma_x": 0.2947683869751587,
        "rotated_sigma_y": 0.05217519674561585,
        "rotation_angle_mrad": -0.0036177886307884647
    },
    "14185": {
        "target_position": -0.5,
        "rotated_mean_x": 0.0209588551632787,
        "rotated_mean_y": 0.03279295494745986,
        "rotated_sigma_x": 0.29795499195765546,
        "rotated_sigma_y": 0.05437479832771459,
        "rotation_angle_mrad": -0.006931114421819586
    },
    "14191": {
        "target_position": -0.5,
        "rotated_mean_x": -0.007290103413763829,
        "rotated_mean_y": 0.043147283523032195,
        "rotated_sigma_x": 0.29553082296769934,
        "rotated_sigma_y": 0.05122135470489806,
        "rotation_angle_mrad": -0.008560645977951928
    },
    "14192": {
        "target_position": -0.5,
        "rotated_mean_x": 0.027162737665538707,
        "rotated_mean_y": 0.05695319002827455,
        "rotated_sigma_x": 0.28970627691653095,
        "rotated_sigma_y": 0.05037309906553549,
        "rotation_angle_mrad": -0.008348741446200758
    },
    "14193": {
        "target_position": -0.5,
        "rotated_mean_x": -0.005947241342866659,
        "rotated_mean_y": 0.042823876793731695,
        "rotated_sigma_x": 0.28811467374635175,
        "rotated_sigma_y": 0.050047653986718954,
        "rotation_angle_mrad": -0.006894868440552614
    },
    "14194": {
        "target_position": -0.5,
        "rotated_mean_x": -0.027678729851866257,
        "rotated_mean_y": 0.03917817842066254,
        "rotated_sigma_x": 0.2867119851642005,
        "rotated_sigma_y": 0.05051123336872467,
        "rotation_angle_mrad": -0.006411376232713989
    },
    "14200": {
        "target_position": -0.5,
        "rotated_mean_x": 0.02068510682601819,
        "rotated_mean_y": 0.02903222333405383,
        "rotated_sigma_x": 0.2914767587993935,
        "rotated_sigma_y": 0.05022300612450401,
        "rotation_angle_mrad": -0.004336829803253344
    },
    "14201": {
        "target_position": -0.5,
        "rotated_mean_x": 0.026237931820784887,
        "rotated_mean_y": 0.026274870189347634,
        "rotated_sigma_x": 0.2897631749655525,
        "rotated_sigma_y": 0.049980143693469314,
        "rotation_angle_mrad": -0.0025189779966528305
    },
    "14204": {
        "target_position": -0.5,
        "rotated_mean_x": 0.0043328871829473705,
        "rotated_mean_y": 0.03167732373665135,
        "rotated_sigma_x": 0.2865052967895936,
        "rotated_sigma_y": 0.049620006377669175,
        "rotation_angle_mrad": -0.0007976654121224866
    },
    "14205": {
        "target_position": -0.5,
        "rotated_mean_x": 0.11199283911541033,
        "rotated_mean_y": 0.008632852167626466,
        "rotated_sigma_x": 0.2896668653542553,
        "rotated_sigma_y": 0.050222421090118693,
        "rotation_angle_mrad": -0.007712729400407856
    },
    "14206": {
        "target_position": -0.5,
        "rotated_mean_x": 0.13031069652565636,
        "rotated_mean_y": 0.01958976838899556,
        "rotated_sigma_x": 0.2885786815394878,
        "rotated_sigma_y": 0.049727653087194505,
        "rotation_angle_mrad": -0.005901346677046981
    },
    "14207": {
        "target_position": -0.5,
        "rotated_mean_x": 0.15541594410460174,
        "rotated_mean_y": 0.02001902353321012,
        "rotated_sigma_x": 0.2941852226713496,
        "rotated_sigma_y": 0.04984436202571932,
        "rotation_angle_mrad": -0.00616332615061216
    },
    "14209": {
        "target_position": -0.5,
        "rotated_mean_x": 0.15495523999656263,
        "rotated_mean_y": 0.008409371097111077,
        "rotated_sigma_x": 0.28904141101246067,
        "rotated_sigma_y": 0.049549534039115245,
        "rotation_angle_mrad": -0.006673533691361916
    },
    "14210": {
        "target_position": -0.5,
        "rotated_mean_x": 0.134022434939425,
        "rotated_mean_y": 0.012891719014374185,
        "rotated_sigma_x": 0.28645883398771443,
        "rotated_sigma_y": 0.049924002661800054,
        "rotation_angle_mrad": -0.00650198328621905
    },
    "14211": {
        "target_position": -0.5,
        "rotated_mean_x": 0.12660082251465204,
        "rotated_mean_y": 0.010289438597737408,
        "rotated_sigma_x": 0.29840681822163445,
        "rotated_sigma_y": 0.05189423591165961,
        "rotation_angle_mrad": -0.011214901958977482
    },
    "14213": {
        "target_position": -0.5,
        "rotated_mean_x": 0.14886623322329787,
        "rotated_mean_y": 0.008214670960179284,
        "rotated_sigma_x": 0.2871965318225487,
        "rotated_sigma_y": 0.05040212826542229,
        "rotation_angle_mrad": -0.009545099089079714
    },
    "14217": {
        "target_position": -0.5,
        "rotated_mean_x": 0.033334843383946204,
        "rotated_mean_y": 0.02490014084397456,
        "rotated_sigma_x": 0.30343871412888607,
        "rotated_sigma_y": 0.05287359887348533,
        "rotation_angle_mrad": -0.007724934231581909
    },
    "14219": {
        "target_position": -0.5,
        "rotated_mean_x": 0.12403936886966248,
        "rotated_mean_y": 0.024915475641190045,
        "rotated_sigma_x": 0.31007451910266853,
        "rotated_sigma_y": 0.0538841273609066,
        "rotation_angle_mrad": -0.003177064320560104
    },
    "14222": {
        "target_position": -0.5,
        "rotated_mean_x": 0.13265993274197752,
        "rotated_mean_y": 0.020259212475625597,
        "rotated_sigma_x": 0.29380756404050307,
        "rotated_sigma_y": 0.053477854136273074,
        "rotation_angle_mrad": -0.004142987367674263
    },
    "14226": {
        "target_position": -0.5,
        "rotated_mean_x": 0.10126734783190612,
        "rotated_mean_y": 0.021191012760227043,
        "rotated_sigma_x": 0.2890332599675711,
        "rotated_sigma_y": 0.0520747485600872,
        "rotation_angle_mrad": -0.0009193077808278662
    },
    "14229": {
        "target_position": -0.5,
        "rotated_mean_x": 0.11889120467161832,
        "rotated_mean_y": 0.01839607232697684,
        "rotated_sigma_x": 0.2980663211638391,
        "rotated_sigma_y": 0.052344060053516835,
        "rotation_angle_mrad": -0.0013226730669370437
    },
    "14231": {
        "target_position": -0.5,
        "rotated_mean_x": 0.33784403104170724,
        "rotated_mean_y": 0.0040156716228301435,
        "rotated_sigma_x": 0.42557520450567604,
        "rotated_sigma_y": 0.07954432243268482,
        "rotation_angle_mrad": -0.001711693878205739
    },
    "14232": {
        "target_position": -0.5,
        "rotated_mean_x": 0.10554420171559406,
        "rotated_mean_y": 0.015423493795459394,
        "rotated_sigma_x": 0.29564709031176634,
        "rotated_sigma_y": 0.05169584270266905,
        "rotation_angle_mrad": -0.001709866495764678
    },
    "14243": {
        "target_position": -0.5,
        "rotated_mean_x": 0.14700311921288917,
        "rotated_mean_y": -0.012253348956978204,
        "rotated_sigma_x": 0.28130252240604203,
        "rotated_sigma_y": 0.050902620745036944,
        "rotation_angle_mrad": -0.012909967909022286
    },
    "14244": {
        "target_position": -0.5,
        "rotated_mean_x": 0.176285882172389,
        "rotated_mean_y": -0.0023459231794585563,
        "rotated_sigma_x": 0.3006744951659564,
        "rotated_sigma_y": 0.059580439150680516,
        "rotation_angle_mrad": -0.02231140938328829
    },
    "14245": {
        "target_position": -0.5,
        "rotated_mean_x": 0.14808569561773965,
        "rotated_mean_y": 0.027770758036815536,
        "rotated_sigma_x": 0.2993845584973338,
        "rotated_sigma_y": 0.05217043653840697,
        "rotation_angle_mrad": -0.016185681353967016
    },
    "14256": {
        "target_position": -0.5,
        "rotated_mean_x": 0.1109690281866484,
        "rotated_mean_y": 0.040295476727194794,
        "rotated_sigma_x": 0.29641431254481976,
        "rotated_sigma_y": 0.05054317380977932,
        "rotation_angle_mrad": -0.00876720847690662
    },
    "14257": {
        "target_position": -0.5,
        "rotated_mean_x": 0.0940959191514395,
        "rotated_mean_y": 0.04504391124145453,
        "rotated_sigma_x": 0.2926418285839279,
        "rotated_sigma_y": 0.050232279597362775,
        "rotation_angle_mrad": -0.0029395310033786815
    },
    "14258": {
        "target_position": -0.5,
        "rotated_mean_x": 0.16325769308746813,
        "rotated_mean_y": 0.018548463172202632,
        "rotated_sigma_x": 0.29072586806338996,
        "rotated_sigma_y": 0.051976146613201414,
        "rotation_angle_mrad": -0.013074335834222415
    },
    "14262": {
        "target_position": -0.5,
        "rotated_mean_x": 0.10954694441344232,
        "rotated_mean_y": 0.029477697153538207,
        "rotated_sigma_x": 0.29448104481695786,
        "rotated_sigma_y": 0.05111751932187697,
        "rotation_angle_mrad": -0.004255225943533747
    },
    "14264": {
        "target_position": -0.5,
        "rotated_mean_x": 0.15047595877342154,
        "rotated_mean_y": 0.017750874094039103,
        "rotated_sigma_x": 0.29012242813473754,
        "rotated_sigma_y": 0.05240423135428783,
        "rotation_angle_mrad": -0.006950648362902966
    },
    "14266": {
        "target_position": -0.5,
        "rotated_mean_x": 0.13809836045696866,
        "rotated_mean_y": 0.01653872852574462,
        "rotated_sigma_x": 0.2863552672420051,
        "rotated_sigma_y": 0.051652174279669005,
        "rotation_angle_mrad": -0.007094894321475899
    },
    "14268": {
        "target_position": -0.5,
        "rotated_mean_x": 0.12030305120640016,
        "rotated_mean_y": 0.01972116808669232,
        "rotated_sigma_x": 0.29414438022136563,
        "rotated_sigma_y": 0.05265491496372343,
        "rotation_angle_mrad": -0.0070110705321297625
    },
    "14269": {
        "target_position": -0.5,
        "rotated_mean_x": 0.13081884831963417,
        "rotated_mean_y": 0.018560589704445185,
        "rotated_sigma_x": 0.2951618260865636,
        "rotated_sigma_y": 0.053788425962838324,
        "rotation_angle_mrad": -0.015019789780150937
    },
    "14270": {
        "target_position": -0.5,
        "rotated_mean_x": 0.3409263619726762,
        "rotated_mean_y": 0.0015706432340801637,
        "rotated_sigma_x": 0.4408065870252132,
        "rotated_sigma_y": 0.07513102009274811,
        "rotation_angle_mrad": -0.007192246405786199
    },
    "14271": {
        "target_position": -0.5,
        "rotated_mean_x": 0.12176278195150293,
        "rotated_mean_y": 0.02151899155781723,
        "rotated_sigma_x": 0.30139250311507876,
        "rotated_sigma_y": 0.05344870513615577,
        "rotation_angle_mrad": -0.013127766894727085
    },
    "14272": {
        "target_position": -0.5,
        "rotated_mean_x": 0.16547621154923564,
        "rotated_mean_y": 0.0157196129180798,
        "rotated_sigma_x": 0.2928441279569949,
        "rotated_sigma_y": 0.05283497225985354,
        "rotation_angle_mrad": -0.0048337167269182505
    },
    "14277": {
        "target_position": -0.5,
        "rotated_mean_x": 0.12176174580374827,
        "rotated_mean_y": 0.023479726144360297,
        "rotated_sigma_x": 0.26470302482032687,
        "rotated_sigma_y": 0.0502527268031859,
        "rotation_angle_mrad": -0.0010591522292128972
    },
    "14282": {
        "target_position": -0.5,
        "rotated_mean_x": 0.10150276713312903,
        "rotated_mean_y": 0.020421389296133415,
        "rotated_sigma_x": 0.300003582313955,
        "rotated_sigma_y": 0.05507874433885091,
        "rotation_angle_mrad": -0.006133696818474789
    },
    "14283": {
        "target_position": -0.5,
        "rotated_mean_x": 0.10616747635974895,
        "rotated_mean_y": 0.027433833592088862,
        "rotated_sigma_x": 0.2953884423024652,
        "rotated_sigma_y": 0.0549312718787169,
        "rotation_angle_mrad": -0.005972666808917204
    },
    "14285": {
        "target_position": -0.5,
        "rotated_mean_x": 0.14169329292852217,
        "rotated_mean_y": 0.016278353342269566,
        "rotated_sigma_x": 0.29611329083637095,
        "rotated_sigma_y": 0.05480833559345428,
        "rotation_angle_mrad": -0.006500883068468531
    },
    "14286": {
        "target_position": -0.5,
        "rotated_mean_x": 0.34069932579514073,
        "rotated_mean_y": 0.0026149269970262455,
        "rotated_sigma_x": 0.4361197600926945,
        "rotated_sigma_y": 0.0779746610848139,
        "rotation_angle_mrad": -0.0027388842661436427
    },
    "14287": {
        "target_position": -0.5,
        "rotated_mean_x": 0.09810567721803833,
        "rotated_mean_y": 0.010621584211414525,
        "rotated_sigma_x": 0.29157975789524415,
        "rotated_sigma_y": 0.05480170780201639,
        "rotation_angle_mrad": -0.002645167374924022
    },
    "14288": {
        "target_position": -0.5,
        "rotated_mean_x": 0.12251069649743987,
        "rotated_mean_y": 0.022596022562219147,
        "rotated_sigma_x": 0.29311778384444653,
        "rotated_sigma_y": 0.055018021538218595,
        "rotation_angle_mrad": -0.0018053327831043567
    },
    "14289": {
        "target_position": -0.5,
        "rotated_mean_x": 0.1301388009451641,
        "rotated_mean_y": 0.01925972468936377,
        "rotated_sigma_x": 0.2950764890547383,
        "rotated_sigma_y": 0.05429633711854374,
        "rotation_angle_mrad": -0.0020373330907235182
    },
    "14290": {
        "target_position": -0.5,
        "rotated_mean_x": 0.31602376351268174,
        "rotated_mean_y": 0.0010966414299745518,
        "rotated_sigma_x": 0.41733060862228233,
        "rotated_sigma_y": 0.049805973104414036,
        "rotation_angle_mrad": -0.005502446793757475
    },
    "14291": {
        "target_position": -0.5,
        "rotated_mean_x": 0.2940672221625284,
        "rotated_mean_y": 0.010828718835080863,
        "rotated_sigma_x": 0.42153978507289663,
        "rotated_sigma_y": 0.05527177558559118,
        "rotation_angle_mrad": -0.004545419146869409
    },
    "14294": {
        "target_position": -0.5,
        "rotated_mean_x": 0.07655733114522491,
        "rotated_mean_y": 0.061015889700946534,
        "rotated_sigma_x": 0.2975766500634348,
        "rotated_sigma_y": 0.05592828436446039,
        "rotation_angle_mrad": -0.0001977270613610277
    },
    "14296": {
        "target_position": -0.5,
        "rotated_mean_x": 0.11869681730934814,
        "rotated_mean_y": 0.059746859339354,
        "rotated_sigma_x": 0.2938460897494829,
        "rotated_sigma_y": 0.056930968417944205,
        "rotation_angle_mrad": -0.00916024955709197
    },
    "14297": {
        "target_position": -0.5,
        "rotated_mean_x": 0.10461125728793526,
        "rotated_mean_y": 0.006675467922494287,
        "rotated_sigma_x": 0.29796946718342004,
        "rotated_sigma_y": 0.05773482858590462,
        "rotation_angle_mrad": -0.007496122553965066
    },
    "14299": {
        "target_position": -0.5,
        "rotated_mean_x": 0.0863490840413498,
        "rotated_mean_y": 0.010051570980580812,
        "rotated_sigma_x": 0.2987430516411352,
        "rotated_sigma_y": 0.05939330083053777,
        "rotation_angle_mrad": -0.008031722409232086
    },
    "14303": {
        "target_position": -0.5,
        "rotated_mean_x": 0.3444250900157069,
        "rotated_mean_y": 0.0035702517111270023,
        "rotated_sigma_x": 0.44060089305084293,
        "rotated_sigma_y": 0.08213449404189216,
        "rotation_angle_mrad": -0.004024440355599995
    },
    "14305": {
        "target_position": -0.5,
        "rotated_mean_x": 0.12545849692978717,
        "rotated_mean_y": 0.017981428519575064,
        "rotated_sigma_x": 0.31130151363966424,
        "rotated_sigma_y": 0.05848218056870571,
        "rotation_angle_mrad": -0.017303222438658845
    },
    "14306": {
        "target_position": -0.5,
        "rotated_mean_x": 0.12445129529812403,
        "rotated_mean_y": 0.029189436153387666,
        "rotated_sigma_x": 0.2963212314360486,
        "rotated_sigma_y": 0.055939746649838945,
        "rotation_angle_mrad": -0.005640259738968662
    },
    "14307": {
        "target_position": -0.5,
        "rotated_mean_x": 0.1401954714319458,
        "rotated_mean_y": 0.017774540905016553,
        "rotated_sigma_x": 0.28744588950377753,
        "rotated_sigma_y": 0.05530208131577592,
        "rotation_angle_mrad": -7.360277546530627e-05
    },
    "14310": {
        "target_position": -0.5,
        "rotated_mean_x": 0.14327600062317322,
        "rotated_mean_y": 0.017116429178269717,
        "rotated_sigma_x": 0.3003339389646728,
        "rotated_sigma_y": 0.05726733546840832,
        "rotation_angle_mrad": -0.0031992453182542757
    },
    "14311": {
        "target_position": -0.5,
        "rotated_mean_x": 0.3481607188058371,
        "rotated_mean_y": 0.0030172856861681594,
        "rotated_sigma_x": 0.43905818394101837,
        "rotated_sigma_y": 0.08258269576799428,
        "rotation_angle_mrad": -0.003477591036317549
    },
    "14312": {
        "target_position": -0.5,
        "rotated_mean_x": 0.12601899163645128,
        "rotated_mean_y": 0.016547228972091012,
        "rotated_sigma_x": 0.3071546985275867,
        "rotated_sigma_y": 0.057607783975296895,
        "rotation_angle_mrad": -0.0128235273098235
    },
    "14313": {
        "target_position": -0.5,
        "rotated_mean_x": 0.1526942297629793,
        "rotated_mean_y": 0.014284918893118208,
        "rotated_sigma_x": 0.3055688813511468,
        "rotated_sigma_y": 0.059386787070629214,
        "rotation_angle_mrad": -0.0034268208601327564
    },
    "14314": {
        "target_position": -0.5,
        "rotated_mean_x": 0.35470846060195754,
        "rotated_mean_y": 0.0034324238938479293,
        "rotated_sigma_x": 0.4421385248663007,
        "rotated_sigma_y": 0.08634862805271512,
        "rotation_angle_mrad": -0.0004267649322802176
    },
    "14315": {
        "target_position": -0.5,
        "rotated_mean_x": 0.16960154260869814,
        "rotated_mean_y": 0.03917979318205897,
        "rotated_sigma_x": 0.2994176864493273,
        "rotated_sigma_y": 0.05795672680017415,
        "rotation_angle_mrad": -0.005685735683576767
    },
    "14316": {
        "target_position": -0.5,
        "rotated_mean_x": 0.13681165981754137,
        "rotated_mean_y": 0.01860652702071345,
        "rotated_sigma_x": 0.2989032877618514,
        "rotated_sigma_y": 0.058073379728742075,
        "rotation_angle_mrad": -0.00414842359395869
    },
    "14318": {
        "target_position": -0.5,
        "rotated_mean_x": 0.35221679683557894,
        "rotated_mean_y": 0.002961186694804381,
        "rotated_sigma_x": 0.43849744891583703,
        "rotated_sigma_y": 0.08266059675784836,
        "rotation_angle_mrad": -0.002794159530261289
    },
    "14319": {
        "target_position": -0.5,
        "rotated_mean_x": 0.11826636376086792,
        "rotated_mean_y": 0.03225135145077217,
        "rotated_sigma_x": 0.2988373737341003,
        "rotated_sigma_y": 0.05753281879286434,
        "rotation_angle_mrad": -0.0035816684368340707
    },
    "14320": {
        "target_position": -0.5,
        "rotated_mean_x": 0.13390040899650793,
        "rotated_mean_y": 0.032745929536135227,
        "rotated_sigma_x": 0.3035855203333676,
        "rotated_sigma_y": 0.05731927718983745,
        "rotation_angle_mrad": -0.005888038609263974
    },
    "14323": {
        "target_position": -0.5,
        "rotated_mean_x": 0.14244519948861958,
        "rotated_mean_y": 0.03593923107481659,
        "rotated_sigma_x": 0.2944797932501716,
        "rotated_sigma_y": 0.05720913746665863,
        "rotation_angle_mrad": -0.004748664178833717
    },
    "14325": {
        "target_position": -0.5,
        "rotated_mean_x": 0.1354343221452005,
        "rotated_mean_y": 0.028995142811464533,
        "rotated_sigma_x": 0.294928382815953,
        "rotated_sigma_y": 0.05744407684066323,
        "rotation_angle_mrad": -0.00505584531114455
    },
    "14326": {
        "target_position": -0.5,
        "rotated_mean_x": 0.11919675617107554,
        "rotated_mean_y": 0.03303686633195854,
        "rotated_sigma_x": 0.29877741244895273,
        "rotated_sigma_y": 0.05833105442997177,
        "rotation_angle_mrad": -0.006409432784562281
    },
    "14327": {
        "target_position": -0.5,
        "rotated_mean_x": 0.1341804407284614,
        "rotated_mean_y": 0.04218475342148974,
        "rotated_sigma_x": 0.2951447919058769,
        "rotated_sigma_y": 0.05934452592066087,
        "rotation_angle_mrad": -0.0007394881324696077
    },
    "14328": {
        "target_position": -0.5,
        "rotated_mean_x": 0.1227400495366412,
        "rotated_mean_y": 0.043829192675086094,
        "rotated_sigma_x": 0.2942877134279621,
        "rotated_sigma_y": 0.061308215428961636,
        "rotation_angle_mrad": -0.00243878731971294
    },
    "14329": {
        "target_position": -0.5,
        "rotated_mean_x": 0.1308465372896494,
        "rotated_mean_y": 0.03466477552071859,
        "rotated_sigma_x": 0.29976381670029323,
        "rotated_sigma_y": 0.05888760142086711,
        "rotation_angle_mrad": -0.004227280888815528
    },
    "14330": {
        "target_position": -0.5,
        "rotated_mean_x": 0.12582999044311705,
        "rotated_mean_y": 0.02752456074879607,
        "rotated_sigma_x": 0.29774545877173597,
        "rotated_sigma_y": 0.05904493261309847,
        "rotation_angle_mrad": -0.00841717008095038
    },
    "14332": {
        "target_position": -0.5,
        "rotated_mean_x": 0.15946237482184722,
        "rotated_mean_y": 0.03811886061045848,
        "rotated_sigma_x": 0.3033231799803881,
        "rotated_sigma_y": 0.05982265570200255,
        "rotation_angle_mrad": -0.0024557386229234137
    },
    "14334": {
        "target_position": -0.5,
        "rotated_mean_x": 0.1483453230915525,
        "rotated_mean_y": 0.03657305034314414,
        "rotated_sigma_x": 0.29580178515766503,
        "rotated_sigma_y": 0.059198296168830156,
        "rotation_angle_mrad": -0.0030252567588345083
    },
    "14335": {
        "target_position": -0.5,
        "rotated_mean_x": 0.172555445844231,
        "rotated_mean_y": 0.03711200013640823,
        "rotated_sigma_x": 0.3011820258816194,
        "rotated_sigma_y": 0.05982345580369799,
        "rotation_angle_mrad": -0.003274968558677304
    },
    "14337": {
        "target_position": -0.5,
        "rotated_mean_x": 0.17606949587568546,
        "rotated_mean_y": 0.03189049516426136,
        "rotated_sigma_x": 0.301972966133115,
        "rotated_sigma_y": 0.05936621570284771,
        "rotation_angle_mrad": -0.0037659479571816312
    },
    "14338": {
        "target_position": -0.5,
        "rotated_mean_x": -0.13193451287929261,
        "rotated_mean_y": 0.0367353075758782,
        "rotated_sigma_x": 0.3040236904811322,
        "rotated_sigma_y": 0.06076736757643577,
        "rotation_angle_mrad": -0.00021345058320172008
    },
    "14339": {
        "target_position": -0.5,
        "rotated_mean_x": -0.15413160253299196,
        "rotated_mean_y": 0.03352331390748388,
        "rotated_sigma_x": 0.29757869327799064,
        "rotated_sigma_y": 0.059862514618256556,
        "rotation_angle_mrad": -0.005338045068535082
    },
    "14340": {
        "target_position": -0.5,
        "rotated_mean_x": -0.16700294969786578,
        "rotated_mean_y": 0.027692291234989817,
        "rotated_sigma_x": 0.30072579906314045,
        "rotated_sigma_y": 0.060163850646492344,
        "rotation_angle_mrad": -0.004281471672687377
    },
    "14342": {
        "target_position": -0.5,
        "rotated_mean_x": -0.17186876957527283,
        "rotated_mean_y": 0.03501169314635002,
        "rotated_sigma_x": 0.29994344816240137,
        "rotated_sigma_y": 0.059783717080130694,
        "rotation_angle_mrad": -6.691007004241762e-05
    },
    "14343": {
        "target_position": -0.5,
        "rotated_mean_x": -0.16387383807794453,
        "rotated_mean_y": 0.036909100548568004,
        "rotated_sigma_x": 0.30118712023788385,
        "rotated_sigma_y": 0.06066122907660007,
        "rotation_angle_mrad": -0.0007553891529600632
    },
    "14344": {
        "target_position": -0.5,
        "rotated_mean_x": -0.17081197147317642,
        "rotated_mean_y": 0.03442794965170934,
        "rotated_sigma_x": 0.30103262044494655,
        "rotated_sigma_y": 0.059329640761459704,
        "rotation_angle_mrad": -0.0008620288178834016
    },
    "14345": {
        "target_position": -0.5,
        "rotated_mean_x": -0.16638749610887582,
        "rotated_mean_y": 0.034450360989300335,
        "rotated_sigma_x": 0.30363332329935977,
        "rotated_sigma_y": 0.05957672092108749,
        "rotation_angle_mrad": -0.0020228942901821256
    },
    "14346": {
        "target_position": -0.5,
        "rotated_mean_x": -0.16989667747837528,
        "rotated_mean_y": 0.028995265940556004,
        "rotated_sigma_x": 0.3015943926948236,
        "rotated_sigma_y": 0.05992791981933943,
        "rotation_angle_mrad": -0.0036369600220878396
    },
    "14347": {
        "target_position": -0.5,
        "rotated_mean_x": -0.08277714190090263,
        "rotated_mean_y": 0.018578438174747795,
        "rotated_sigma_x": 0.30129288204179105,
        "rotated_sigma_y": 0.060037400923802664,
        "rotation_angle_mrad": -0.0013651691409723382
    },
    "14348": {
        "target_position": -0.5,
        "rotated_mean_x": -0.17461900061831492,
        "rotated_mean_y": 0.02536402286925134,
        "rotated_sigma_x": 0.30290015954376126,
        "rotated_sigma_y": 0.06181319471960741,
        "rotation_angle_mrad": -0.0017112556188520348
    },
    "14349": {
        "target_position": -0.5,
        "rotated_mean_x": -0.17473262274020449,
        "rotated_mean_y": 0.023950996161984085,
        "rotated_sigma_x": 0.30266415279837566,
        "rotated_sigma_y": 0.05988506866262426,
        "rotation_angle_mrad": -0.002234036007738294
    },
    "14350": {
        "target_position": -0.5,
        "rotated_mean_x": -0.18435098987780985,
        "rotated_mean_y": 0.006936372450307913,
        "rotated_sigma_x": 0.43883578266099804,
        "rotated_sigma_y": 0.0898263978932389,
        "rotation_angle_mrad": -0.002940914637472561
    },
    "14351": {
        "target_position": -0.5,
        "rotated_mean_x": -0.17332434581739387,
        "rotated_mean_y": 0.02783139878039084,
        "rotated_sigma_x": 0.29987302478723127,
        "rotated_sigma_y": 0.06052984669177881,
        "rotation_angle_mrad": -0.0005468383367013345
    },
    "14354": {
        "target_position": -0.5,
        "rotated_mean_x": -0.17877429310581203,
        "rotated_mean_y": 0.09794471633394743,
        "rotated_sigma_x": 0.30833001643614,
        "rotated_sigma_y": 0.05951381133516761,
        "rotation_angle_mrad": -0.00688835307927053
    },
    "14355": {
        "target_position": -0.5,
        "rotated_mean_x": -0.17113929083983137,
        "rotated_mean_y": 0.09503035965483846,
        "rotated_sigma_x": 0.30495448829958605,
        "rotated_sigma_y": 0.059989371502101735,
        "rotation_angle_mrad": -0.002097830183855257
    },
    "14357": {
        "target_position": -0.5,
        "rotated_mean_x": 0.1564660281275116,
        "rotated_mean_y": 0.10271171986910509,
        "rotated_sigma_x": 0.3023983887806327,
        "rotated_sigma_y": 0.058485983857313614,
        "rotation_angle_mrad": -0.0015322536263328466
    },
    "14358": {
        "target_position": -0.5,
        "rotated_mean_x": 0.14223133899976176,
        "rotated_mean_y": 0.10382332824146927,
        "rotated_sigma_x": 0.29402751496341867,
        "rotated_sigma_y": 0.04936772231648712,
        "rotation_angle_mrad": -0.010861824841834133
    },
    "14359": {
        "target_position": -0.5,
        "rotated_mean_x": 0.19698878074895923,
        "rotated_mean_y": 0.09660720476553755,
        "rotated_sigma_x": 0.3004786864359511,
        "rotated_sigma_y": 0.05439575837506267,
        "rotation_angle_mrad": -0.005133868285156394
    },
    "14360": {
        "target_position": -0.5,
        "rotated_mean_x": 0.1811607417667854,
        "rotated_mean_y": 0.09993268448324524,
        "rotated_sigma_x": 0.30594447370736116,
        "rotated_sigma_y": 0.053915356694489325,
        "rotation_angle_mrad": -0.004842073932196963
    },
    "14367": {
        "target_position": -0.5,
        "rotated_mean_x": 0.15511474330329242,
        "rotated_mean_y": 0.0867052901873843,
        "rotated_sigma_x": 0.2990589582232901,
        "rotated_sigma_y": 0.055049938475510984,
        "rotation_angle_mrad": -0.0003527684031635939
    },
    "14368": {
        "target_position": -0.5,
        "rotated_mean_x": 0.14815970383284893,
        "rotated_mean_y": 0.09035225781230549,
        "rotated_sigma_x": 0.28912891434312243,
        "rotated_sigma_y": 0.05279944849191638,
        "rotation_angle_mrad": -0.000308204410499584
    },
    "14369": {
        "target_position": -0.5,
        "rotated_mean_x": 0.15178201713680617,
        "rotated_mean_y": 0.10297237479304197,
        "rotated_sigma_x": 0.2970759191258044,
        "rotated_sigma_y": 0.05349490308624153,
        "rotation_angle_mrad": -7.599565330117442e-05
    },
    "14381": {
        "target_position": -0.5,
        "rotated_mean_x": 0.14656582666771156,
        "rotated_mean_y": 0.07163123964940002,
        "rotated_sigma_x": 0.30178119848518487,
        "rotated_sigma_y": 0.051474621889693074,
        "rotation_angle_mrad": -0.007580476645570589
    },
    "14382": {
        "target_position": -0.5,
        "rotated_mean_x": 0.17241607024852817,
        "rotated_mean_y": 0.09055538918566765,
        "rotated_sigma_x": 0.29271306053930884,
        "rotated_sigma_y": 0.049911842618413506,
        "rotation_angle_mrad": -0.007911217564959211
    },
    "14389": {
        "target_position": -0.5,
        "rotated_mean_x": 0.16743276272556876,
        "rotated_mean_y": 0.07958661846088401,
        "rotated_sigma_x": 0.3027301717751373,
        "rotated_sigma_y": 0.05162685049565154,
        "rotation_angle_mrad": -0.010772335167699196
    },
    "14391": {
        "target_position": -0.5,
        "rotated_mean_x": 0.152994045575859,
        "rotated_mean_y": 0.0900102036890727,
        "rotated_sigma_x": 0.29201616329278013,
        "rotated_sigma_y": 0.049781987475714745,
        "rotation_angle_mrad": -0.007044862961475968
    },
    "14394": {
        "target_position": -0.5,
        "rotated_mean_x": 0.1625881998091217,
        "rotated_mean_y": 0.08620196740723439,
        "rotated_sigma_x": 0.2963985756860514,
        "rotated_sigma_y": 0.0515923408487842,
        "rotation_angle_mrad": -0.005991556381731718
    },
    "14395": {
        "target_position": -0.5,
        "rotated_mean_x": 0.17513589660692797,
        "rotated_mean_y": 0.09438606560068108,
        "rotated_sigma_x": 0.30387475038974693,
        "rotated_sigma_y": 0.052174480370106864,
        "rotation_angle_mrad": -0.010987341065030678
    },
    "14401": {
        "target_position": -0.5,
        "rotated_mean_x": 0.16785425698623965,
        "rotated_mean_y": 0.09870785720874518,
        "rotated_sigma_x": 0.297227126807347,
        "rotated_sigma_y": 0.051573185449230265,
        "rotation_angle_mrad": -0.007007006262430677
    },
    "14402": {
        "target_position": -0.5,
        "rotated_mean_x": 0.15497021623862414,
        "rotated_mean_y": 0.08714378622874931,
        "rotated_sigma_x": 0.29825593941343653,
        "rotated_sigma_y": 0.05401393476026794,
        "rotation_angle_mrad": -0.0012257472273856825
    },
    "14407": {
        "target_position": -0.5,
        "rotated_mean_x": 0.16268932778059728,
        "rotated_mean_y": 0.08859407175156817,
        "rotated_sigma_x": 0.29901411708424513,
        "rotated_sigma_y": 0.05149498145440803,
        "rotation_angle_mrad": -0.006105920101132363
    },
    "14408": {
        "target_position": -0.5,
        "rotated_mean_x": 0.17146139028349455,
        "rotated_mean_y": 0.09730626466323371,
        "rotated_sigma_x": 0.2979604021634927,
        "rotated_sigma_y": 0.05307702759713568,
        "rotation_angle_mrad": -0.005947450943147546
    },
    "14412": {
        "target_position": -0.5,
        "rotated_mean_x": 0.16053543111200821,
        "rotated_mean_y": 0.11580183509163688,
        "rotated_sigma_x": 0.29142718457533295,
        "rotated_sigma_y": 0.05118911340571796,
        "rotation_angle_mrad": -0.010289036707530409
    },
    "14413": {
        "target_position": -0.5,
        "rotated_mean_x": 0.18343000183255595,
        "rotated_mean_y": 0.1229256226529316,
        "rotated_sigma_x": 0.2927701417592904,
        "rotated_sigma_y": 0.05312840094600399,
        "rotation_angle_mrad": -0.010491946747118598
    },
    "14414": {
        "target_position": -0.5,
        "rotated_mean_x": 0.17755038911647011,
        "rotated_mean_y": 0.10772612798437234,
        "rotated_sigma_x": 0.30550173517062723,
        "rotated_sigma_y": 0.05444342222648712,
        "rotation_angle_mrad": -0.013532734157684152
    },
    "14415": {
        "target_position": -0.5,
        "rotated_mean_x": 0.1744315861984461,
        "rotated_mean_y": 0.09966760093510607,
        "rotated_sigma_x": 0.2988748592898763,
        "rotated_sigma_y": 0.052979551887408036,
        "rotation_angle_mrad": -0.01376636775904179
    },
    "14416": {
        "target_position": -0.5,
        "rotated_mean_x": 0.16482515806516698,
        "rotated_mean_y": 0.11568574580824949,
        "rotated_sigma_x": 0.2945235027968425,
        "rotated_sigma_y": 0.053010845799052735,
        "rotation_angle_mrad": -0.01628430406285345
    },
    "14417": {
        "target_position": -0.5,
        "rotated_mean_x": 0.15408545095041845,
        "rotated_mean_y": 0.11870107710620076,
        "rotated_sigma_x": 0.30509318631201393,
        "rotated_sigma_y": 0.05209870115698594,
        "rotation_angle_mrad": -0.015680431504789035
    },
    "14419": {
        "target_position": -0.5,
        "rotated_mean_x": 0.1684004374738522,
        "rotated_mean_y": 0.10511354456641459,
        "rotated_sigma_x": 0.30912514317106454,
        "rotated_sigma_y": 0.05541154101508,
        "rotation_angle_mrad": -0.01780123250373895
    },
    "14420": {
        "target_position": -0.5,
        "rotated_mean_x": 0.15189805460492764,
        "rotated_mean_y": 0.11089902559424879,
        "rotated_sigma_x": 0.2932001903232397,
        "rotated_sigma_y": 0.05176196419362596,
        "rotation_angle_mrad": -0.005813847725082374
    },
    "14421": {
        "target_position": -0.5,
        "rotated_mean_x": 0.1877199296117866,
        "rotated_mean_y": 0.09406696990880599,
        "rotated_sigma_x": 0.2999085163519634,
        "rotated_sigma_y": 0.05374684806145883,
        "rotation_angle_mrad": -0.011993507689464033
    },
    "14423": {
        "target_position": -0.5,
        "rotated_mean_x": 0.1575649184434145,
        "rotated_mean_y": 0.10188682334339055,
        "rotated_sigma_x": 0.2984638315917356,
        "rotated_sigma_y": 0.05365667940352642,
        "rotation_angle_mrad": -0.011800513070241011
    },
    "14425": {
        "target_position": -0.5,
        "rotated_mean_x": 0.18453903142275793,
        "rotated_mean_y": 0.12269688827036865,
        "rotated_sigma_x": 0.30635226229802076,
        "rotated_sigma_y": 0.054192952807502894,
        "rotation_angle_mrad": -0.016108016926565744
    },
    "14426": {
        "target_position": -0.5,
        "rotated_mean_x": 0.18676213066636332,
        "rotated_mean_y": 0.09503986466055869,
        "rotated_sigma_x": 0.29814947823791166,
        "rotated_sigma_y": 0.057185696554654886,
        "rotation_angle_mrad": -0.015771185453954773
    },
    "14427": {
        "target_position": -0.5,
        "rotated_mean_x": 0.16935983241525146,
        "rotated_mean_y": 0.1639087263439219,
        "rotated_sigma_x": 0.4558592162776282,
        "rotated_sigma_y": 0.19312733500949614,
        "rotation_angle_mrad": -0.04100702258302919
    },
    "14428": {
        "target_position": -0.5,
        "rotated_mean_x": 0.1566136386920199,
        "rotated_mean_y": 0.1079391061108291,
        "rotated_sigma_x": 0.3012356893122059,
        "rotated_sigma_y": 0.05490045100200367,
        "rotation_angle_mrad": -0.017919728526934804
    },
    "14430": {
        "target_position": -0.5,
        "rotated_mean_x": 0.16188918399191238,
        "rotated_mean_y": 0.11482508130851164,
        "rotated_sigma_x": 0.29983721572936445,
        "rotated_sigma_y": 0.055207441875408825,
        "rotation_angle_mrad": -0.01700163636450689
    },
    "14431": {
        "target_position": -0.5,
        "rotated_mean_x": 0.17444929311835475,
        "rotated_mean_y": 0.10633368579695648,
        "rotated_sigma_x": 0.29302657209664473,
        "rotated_sigma_y": 0.0559741057491243,
        "rotation_angle_mrad": -0.02130293036936407
    },
    "14432": {
        "target_position": -0.5,
        "rotated_mean_x": 0.19188877625391584,
        "rotated_mean_y": 0.11337342099305639,
        "rotated_sigma_x": 0.2957761378221474,
        "rotated_sigma_y": 0.05658548756374441,
        "rotation_angle_mrad": -0.022891160974609092
    },
    "14433": {
        "target_position": -0.5,
        "rotated_mean_x": 0.17596017844552855,
        "rotated_mean_y": 0.11584197939366528,
        "rotated_sigma_x": 0.2966449148670658,
        "rotated_sigma_y": 0.057382780360545615,
        "rotation_angle_mrad": -0.02280496626031252
    },
    "14434": {
        "target_position": -0.5,
        "rotated_mean_x": 0.19875789352776008,
        "rotated_mean_y": 0.11860498287755152,
        "rotated_sigma_x": 0.29939876793598275,
        "rotated_sigma_y": 0.0589779575555412,
        "rotation_angle_mrad": -0.022058671860975515
    },
    "14441": {
        "target_position": -0.5,
        "rotated_mean_x": 0.19777123065475893,
        "rotated_mean_y": 0.0890746369685821,
        "rotated_sigma_x": 0.3021188790412672,
        "rotated_sigma_y": 0.058591513092802874,
        "rotation_angle_mrad": -0.01687508656765703
    },
    "14442": {
        "target_position": -0.5,
        "rotated_mean_x": 0.189794112212406,
        "rotated_mean_y": 0.08151580119692564,
        "rotated_sigma_x": 0.30162612012714635,
        "rotated_sigma_y": 0.05798714537980565,
        "rotation_angle_mrad": -0.016482827362527316
    },
    "14443": {
        "target_position": -0.5,
        "rotated_mean_x": 0.17744039334348208,
        "rotated_mean_y": 0.10012086456686073,
        "rotated_sigma_x": 0.309078772601944,
        "rotated_sigma_y": 0.057508258911606006,
        "rotation_angle_mrad": -0.019342984385012613
    },
    "14444": {
        "target_position": -0.5,
        "rotated_mean_x": 0.19131739820455637,
        "rotated_mean_y": 0.08047923510052829,
        "rotated_sigma_x": 0.3014507310799429,
        "rotated_sigma_y": 0.05981463206151679,
        "rotation_angle_mrad": -0.01967311089623429
    },
    "14449": {
        "target_position": -0.5,
        "rotated_mean_x": 0.1779189123625238,
        "rotated_mean_y": 0.11235407133996256,
        "rotated_sigma_x": 0.2975788677750411,
        "rotated_sigma_y": 0.06468130174167243,
        "rotation_angle_mrad": -0.0065933102363132145
    },
    "14451": {
        "target_position": -0.5,
        "rotated_mean_x": 0.16293312257503514,
        "rotated_mean_y": 0.10404467458719943,
        "rotated_sigma_x": 0.29340532553268844,
        "rotated_sigma_y": 0.05413519898884316,
        "rotation_angle_mrad": -0.012151019557280998
    },
    "14454": {
        "target_position": -0.5,
        "rotated_mean_x": 0.21337468049562017,
        "rotated_mean_y": 0.06169481300227848,
        "rotated_sigma_x": 0.2920812846259152,
        "rotated_sigma_y": 0.05458430475339208,
        "rotation_angle_mrad": -0.013638558392127522
    },
    "14455": {
        "target_position": -0.5,
        "rotated_mean_x": 0.19653665366466164,
        "rotated_mean_y": 0.07332730839339217,
        "rotated_sigma_x": 0.29411202199990427,
        "rotated_sigma_y": 0.055586009478089844,
        "rotation_angle_mrad": -0.013694426265778544
    },
    "14457": {
        "target_position": -0.5,
        "rotated_mean_x": 0.2012987448276125,
        "rotated_mean_y": 0.06429090774323605,
        "rotated_sigma_x": 0.2941045496735818,
        "rotated_sigma_y": 0.056320370460508064,
        "rotation_angle_mrad": -0.012650881773315588
    },
    "14458": {
        "target_position": -0.5,
        "rotated_mean_x": 0.1908537541236362,
        "rotated_mean_y": 0.06185602712646227,
        "rotated_sigma_x": 0.29415071464664894,
        "rotated_sigma_y": 0.05609599731291618,
        "rotation_angle_mrad": -0.011999394492556307
    },
    "14459": {
        "target_position": -0.5,
        "rotated_mean_x": 0.19716531798324918,
        "rotated_mean_y": 0.0740659364513861,
        "rotated_sigma_x": 0.29070572660233335,
        "rotated_sigma_y": 0.05604284517717524,
        "rotation_angle_mrad": -0.012528268233112963
    },
    "14460": {
        "target_position": -0.5,
        "rotated_mean_x": 0.18993484807647326,
        "rotated_mean_y": 0.06721559397783648,
        "rotated_sigma_x": 0.29690427371590394,
        "rotated_sigma_y": 0.055764151177454785,
        "rotation_angle_mrad": -0.013944115321270167
    },
    "14464": {
        "target_position": -0.5,
        "rotated_mean_x": 0.18925387078079367,
        "rotated_mean_y": 0.059649152480225245,
        "rotated_sigma_x": 0.29087734782744673,
        "rotated_sigma_y": 0.056785588512784556,
        "rotation_angle_mrad": -0.014454998129254855
    },
    "14465": {
        "target_position": -0.5,
        "rotated_mean_x": 0.17698936229100232,
        "rotated_mean_y": 0.06422252001596902,
        "rotated_sigma_x": 0.2959223455821628,
        "rotated_sigma_y": 0.056698690744179846,
        "rotation_angle_mrad": -0.015139642819475819
    },
    "14466": {
        "target_position": -0.5,
        "rotated_mean_x": 0.18747282305066987,
        "rotated_mean_y": 0.06995917391360762,
        "rotated_sigma_x": 0.2983125451258424,
        "rotated_sigma_y": 0.057244354545592194,
        "rotation_angle_mrad": -0.011756647865282509
    },
    "14468": {
        "target_position": -0.5,
        "rotated_mean_x": 0.1647831833318406,
        "rotated_mean_y": 0.07613486086923264,
        "rotated_sigma_x": 0.2918888716961579,
        "rotated_sigma_y": 0.054514637249319486,
        "rotation_angle_mrad": -0.012420851525755904
    },
    "14469": {
        "target_position": -0.5,
        "rotated_mean_x": 0.16623817665095014,
        "rotated_mean_y": 0.10865256370138905,
        "rotated_sigma_x": 0.5661808707135956,
        "rotated_sigma_y": 0.258204739934585,
        "rotation_angle_mrad": -0.06037461823139785
    },
    "14470": {
        "target_position": -0.5,
        "rotated_mean_x": 0.16597671259134264,
        "rotated_mean_y": 0.08370325690772551,
        "rotated_sigma_x": 0.2905516089299712,
        "rotated_sigma_y": 0.053608437268819864,
        "rotation_angle_mrad": -0.011089046412023407
    },
    "14471": {
        "target_position": -0.5,
        "rotated_mean_x": 0.17693501948993207,
        "rotated_mean_y": 0.0770122010389507,
        "rotated_sigma_x": 0.29520106078494607,
        "rotated_sigma_y": 0.05502988886840438,
        "rotation_angle_mrad": -0.01431145730794619
    },
    "14472": {
        "target_position": -0.5,
        "rotated_mean_x": 0.18548963443088798,
        "rotated_mean_y": 0.0756341780265687,
        "rotated_sigma_x": 0.2972859320067504,
        "rotated_sigma_y": 0.057381255102004744,
        "rotation_angle_mrad": -0.015048861634497528
    },
    "14473": {
        "target_position": -0.5,
        "rotated_mean_x": 0.1780329735303602,
        "rotated_mean_y": 0.07650543869510668,
        "rotated_sigma_x": 0.2984039496679595,
        "rotated_sigma_y": 0.05691483300585913,
        "rotation_angle_mrad": -0.013157714798789627
    },
    "14475": {
        "target_position": -0.5,
        "rotated_mean_x": 0.21560323108497,
        "rotated_mean_y": 0.0735215301105679,
        "rotated_sigma_x": 0.28817320602620744,
        "rotated_sigma_y": 0.054737617025552826,
        "rotation_angle_mrad": -0.014942578707771218
    },
    "14476": {
        "target_position": -0.5,
        "rotated_mean_x": 0.20368860492460586,
        "rotated_mean_y": 0.05909053312776795,
        "rotated_sigma_x": 0.29336473424056314,
        "rotated_sigma_y": 0.05560248423578944,
        "rotation_angle_mrad": -0.012400115945782225
    },
    "14482": {
        "target_position": -0.5,
        "rotated_mean_x": 0.1780311613561335,
        "rotated_mean_y": 0.09541810516596003,
        "rotated_sigma_x": 0.29126198007496235,
        "rotated_sigma_y": 0.05367110380743746,
        "rotation_angle_mrad": -0.014491275127555468
    },
    "14483": {
        "target_position": -0.5,
        "rotated_mean_x": 0.1504310892316967,
        "rotated_mean_y": 0.09273352038920908,
        "rotated_sigma_x": 0.2872988114146737,
        "rotated_sigma_y": 0.05410706872503774,
        "rotation_angle_mrad": -0.01752520976925962
    },
    "14484": {
        "target_position": -0.5,
        "rotated_mean_x": 0.17028787332740616,
        "rotated_mean_y": 0.09206893370407344,
        "rotated_sigma_x": 0.2947035024421925,
        "rotated_sigma_y": 0.05527922988893182,
        "rotation_angle_mrad": -0.018486880076896032
    },
    "14485": {
        "target_position": -0.5,
        "rotated_mean_x": 0.15790140480476025,
        "rotated_mean_y": 0.09613421204338463,
        "rotated_sigma_x": 0.2936024463047446,
        "rotated_sigma_y": 0.05521382812734921,
        "rotation_angle_mrad": -0.01679022464823056
    },
    "14486": {
        "target_position": -0.5,
        "rotated_mean_x": 0.14793776443829343,
        "rotated_mean_y": 0.0974181738900646,
        "rotated_sigma_x": 0.2934820993321816,
        "rotated_sigma_y": 0.05560603397708071,
        "rotation_angle_mrad": -0.019965870233566177
    },
    "14487": {
        "target_position": -0.5,
        "rotated_mean_x": 0.16235453657891932,
        "rotated_mean_y": 0.10046604400114431,
        "rotated_sigma_x": 0.28801192924412655,
        "rotated_sigma_y": 0.05448596765627285,
        "rotation_angle_mrad": -0.016133681672396472
    },
    "14490": {
        "target_position": -0.5,
        "rotated_mean_x": 0.17077689464626486,
        "rotated_mean_y": 0.09822897481081973,
        "rotated_sigma_x": 0.2983276724341023,
        "rotated_sigma_y": 0.056139666451162744,
        "rotation_angle_mrad": -0.020050123700011933
    },
    "14491": {
        "target_position": -0.5,
        "rotated_mean_x": 0.18156621246732652,
        "rotated_mean_y": 0.09834351079992838,
        "rotated_sigma_x": 0.2897301463137955,
        "rotated_sigma_y": 0.05585948403395943,
        "rotation_angle_mrad": -0.02086306278581031
    },
    "14492": {
        "target_position": -0.5,
        "rotated_mean_x": 0.1578971341499321,
        "rotated_mean_y": 0.09213301312769749,
        "rotated_sigma_x": 0.30133920215311716,
        "rotated_sigma_y": 0.05688739887962962,
        "rotation_angle_mrad": -0.020241885347312142
    },
    "14493": {
        "target_position": -0.5,
        "rotated_mean_x": 0.12606850385853777,
        "rotated_mean_y": 0.08711711033661314,
        "rotated_sigma_x": 0.29334394817593684,
        "rotated_sigma_y": 0.05714663723573642,
        "rotation_angle_mrad": -0.024016912556700333
    },
    "14495": {
        "target_position": -0.5,
        "rotated_mean_x": 0.15502548575605787,
        "rotated_mean_y": 0.08305494854045523,
        "rotated_sigma_x": 0.2931655420888056,
        "rotated_sigma_y": 0.056264782973100225,
        "rotation_angle_mrad": -0.019340651556705134
    },
    "14496": {
        "target_position": -0.5,
        "rotated_mean_x": 0.16499919170184343,
        "rotated_mean_y": 0.09323707025659818,
        "rotated_sigma_x": 0.3185461259295953,
        "rotated_sigma_y": 0.059130010576209605,
        "rotation_angle_mrad": -0.027628599265912195
    },
    "14497": {
        "target_position": -0.5,
        "rotated_mean_x": 0.2179993691937587,
        "rotated_mean_y": 0.13455211414595317,
        "rotated_sigma_x": 0.2544725464382126,
        "rotated_sigma_y": 0.05238146651792942,
        "rotation_angle_mrad": -0.01630697746414815
    },
    "14501": {
        "target_position": -0.5,
        "rotated_mean_x": 0.20518506568323733,
        "rotated_mean_y": 0.1411724962309245,
        "rotated_sigma_x": 0.26297877566749284,
        "rotated_sigma_y": 0.050479954990214834,
        "rotation_angle_mrad": -0.01663152721161323
    },
    "14504": {
        "target_position": -0.5,
        "rotated_mean_x": 0.20300724428583078,
        "rotated_mean_y": 0.09075344062480678,
        "rotated_sigma_x": 0.29503012035110676,
        "rotated_sigma_y": 0.05632314794985118,
        "rotation_angle_mrad": -0.021006944947430307
    },
    "14505": {
        "target_position": -0.5,
        "rotated_mean_x": 0.18995242257498252,
        "rotated_mean_y": 0.08796999121659185,
        "rotated_sigma_x": 0.2979364145465172,
        "rotated_sigma_y": 0.0568398933118296,
        "rotation_angle_mrad": -0.01904669975945461
    },
    "14506": {
        "target_position": -0.5,
        "rotated_mean_x": 0.1948745114799809,
        "rotated_mean_y": 0.08915319675662078,
        "rotated_sigma_x": 0.2934697861812456,
        "rotated_sigma_y": 0.0567682377749851,
        "rotation_angle_mrad": -0.020223078732918526
    },
    "14507": {
        "target_position": -0.5,
        "rotated_mean_x": 0.20551509423296876,
        "rotated_mean_y": 0.1023701593485772,
        "rotated_sigma_x": 0.2890932395225267,
        "rotated_sigma_y": 0.06147228751904654,
        "rotation_angle_mrad": -0.011480543747161391
    },
    "14508": {
        "target_position": -0.5,
        "rotated_mean_x": 0.15349297710695264,
        "rotated_mean_y": 0.10387179755342535,
        "rotated_sigma_x": 0.2913683359406666,
        "rotated_sigma_y": 0.0540107913643371,
        "rotation_angle_mrad": -0.01606866850116341
    },
    "14512": {
        "target_position": -0.5,
        "rotated_mean_x": 0.1832498073725973,
        "rotated_mean_y": 0.1023792003122926,
        "rotated_sigma_x": 0.29861093439260855,
        "rotated_sigma_y": 0.05531086120560605,
        "rotation_angle_mrad": -0.019178085874553455
    },
    "14513": {
        "target_position": -0.5,
        "rotated_mean_x": 0.2236975860362896,
        "rotated_mean_y": 0.09308229184539882,
        "rotated_sigma_x": 0.2981003811784051,
        "rotated_sigma_y": 0.054556415041215583,
        "rotation_angle_mrad": -0.020978837294011753
    },
    "14514": {
        "target_position": -0.5,
        "rotated_mean_x": 0.19711439602401548,
        "rotated_mean_y": 0.09269112358122492,
        "rotated_sigma_x": 0.2978816702938251,
        "rotated_sigma_y": 0.05608754934663795,
        "rotation_angle_mrad": -0.018248061188313444
    },
    "14515": {
        "target_position": -0.5,
        "rotated_mean_x": 0.20957570732519487,
        "rotated_mean_y": 0.09406411672885306,
        "rotated_sigma_x": 0.30307830289386034,
        "rotated_sigma_y": 0.0568924970358642,
        "rotation_angle_mrad": -0.016910455078571487
    },
    "14516": {
        "target_position": -0.5,
        "rotated_mean_x": 0.20345411804928348,
        "rotated_mean_y": 0.09203492211835383,
        "rotated_sigma_x": 0.2961625390065421,
        "rotated_sigma_y": 0.05633467019764608,
        "rotation_angle_mrad": -0.01833578561593375
    },
    "14520": {
        "target_position": -0.5,
        "rotated_mean_x": 0.20390442462831596,
        "rotated_mean_y": 0.09969243945714971,
        "rotated_sigma_x": 0.2987649663168392,
        "rotated_sigma_y": 0.056191594480881256,
        "rotation_angle_mrad": -0.016051108818525367
    },
    "14521": {
        "target_position": -0.5,
        "rotated_mean_x": 0.18720597272741027,
        "rotated_mean_y": 0.09254867365269763,
        "rotated_sigma_x": 0.2997276109117257,
        "rotated_sigma_y": 0.05677737855858243,
        "rotation_angle_mrad": -0.018238116122496695
    },
    "14522": {
        "target_position": -0.5,
        "rotated_mean_x": 0.1800636771272786,
        "rotated_mean_y": 0.09421597999373316,
        "rotated_sigma_x": 0.2982453884530981,
        "rotated_sigma_y": 0.057014820243624115,
        "rotation_angle_mrad": -0.0169058839871059
    },
    "14533": {
        "target_position": -0.5,
        "rotated_mean_x": 0.1917524322600122,
        "rotated_mean_y": 0.09023767079652431,
        "rotated_sigma_x": 0.3068163619953606,
        "rotated_sigma_y": 0.060029673832719455,
        "rotation_angle_mrad": -0.022134430763118974
    },
    "14534": {
        "target_position": -0.5,
        "rotated_mean_x": 0.17400584213166456,
        "rotated_mean_y": 0.09650532712083057,
        "rotated_sigma_x": 0.2979273280840417,
        "rotated_sigma_y": 0.05297527650820996,
        "rotation_angle_mrad": -0.01843349565414183
    },
    "14536": {
        "target_position": -0.5,
        "rotated_mean_x": 0.17759390181686696,
        "rotated_mean_y": 0.09395219827609383,
        "rotated_sigma_x": 0.3006953725018543,
        "rotated_sigma_y": 0.05471926552932723,
        "rotation_angle_mrad": -0.016957885243728668
    },
    "14537": {
        "target_position": -0.5,
        "rotated_mean_x": 0.15886425562757542,
        "rotated_mean_y": 0.09890993028143777,
        "rotated_sigma_x": 0.29756285713181674,
        "rotated_sigma_y": 0.05432216745861987,
        "rotation_angle_mrad": -0.016245687349309604
    },
    "14538": {
        "target_position": -0.5,
        "rotated_mean_x": 0.16876631476951617,
        "rotated_mean_y": 0.08676857366002848,
        "rotated_sigma_x": 0.2958211052863868,
        "rotated_sigma_y": 0.05373960331068636,
        "rotation_angle_mrad": -0.013473790262385049
    },
    "14539": {
        "target_position": -0.5,
        "rotated_mean_x": 0.18549582807873014,
        "rotated_mean_y": 0.10131529438525617,
        "rotated_sigma_x": 0.29763392005585093,
        "rotated_sigma_y": 0.05638712535763533,
        "rotation_angle_mrad": -0.019440759306924325
    },
    "14540": {
        "target_position": -0.5,
        "rotated_mean_x": 0.18073055809459201,
        "rotated_mean_y": 0.08561862449991989,
        "rotated_sigma_x": 0.2941808800238589,
        "rotated_sigma_y": 0.05438166406134086,
        "rotation_angle_mrad": -0.020744612993296625
    },
    "14541": {
        "target_position": -0.5,
        "rotated_mean_x": 0.20847430766477956,
        "rotated_mean_y": 0.08837920371893594,
        "rotated_sigma_x": 0.2953023616978898,
        "rotated_sigma_y": 0.0559047826784659,
        "rotation_angle_mrad": -0.020006602188893243
    },
    "14542": {
        "target_position": -0.5,
        "rotated_mean_x": 0.1791502275250015,
        "rotated_mean_y": 0.08894430531261946,
        "rotated_sigma_x": 0.29904549690943893,
        "rotated_sigma_y": 0.05501091122870812,
        "rotation_angle_mrad": -0.019877260821847584
    },
    "14543": {
        "target_position": -0.5,
        "rotated_mean_x": 0.1708584815555196,
        "rotated_mean_y": 0.08938585568711041,
        "rotated_sigma_x": 0.30283836984741447,
        "rotated_sigma_y": 0.05673289884556615,
        "rotation_angle_mrad": -0.019628638503239756
    },
    "14544": {
        "target_position": -0.5,
        "rotated_mean_x": 0.18246248125480355,
        "rotated_mean_y": 0.0888119313092997,
        "rotated_sigma_x": 0.30171568897206336,
        "rotated_sigma_y": 0.056655041154678516,
        "rotation_angle_mrad": -0.017993071127494598
    },
    "14545": {
        "target_position": -0.5,
        "rotated_mean_x": 0.1837860716692985,
        "rotated_mean_y": 0.08275850350622539,
        "rotated_sigma_x": 0.30368855377666176,
        "rotated_sigma_y": 0.05692962424227003,
        "rotation_angle_mrad": -0.019249810334222447
    },
    "14546": {
        "target_position": -0.5,
        "rotated_mean_x": 0.17833987747035113,
        "rotated_mean_y": 0.08203739908346652,
        "rotated_sigma_x": 0.28941302846091316,
        "rotated_sigma_y": 0.05572370890974379,
        "rotation_angle_mrad": -0.02029370663353258
    },
    "14547": {
        "target_position": -0.5,
        "rotated_mean_x": 0.18236609099858542,
        "rotated_mean_y": 0.08264912619120234,
        "rotated_sigma_x": 0.2937883477254459,
        "rotated_sigma_y": 0.05642348454150631,
        "rotation_angle_mrad": -0.020932159813911565
    },
    "14548": {
        "target_position": -0.5,
        "rotated_mean_x": 0.18306515958568395,
        "rotated_mean_y": 0.08034818541427043,
        "rotated_sigma_x": 0.3030596034301226,
        "rotated_sigma_y": 0.057948267841786485,
        "rotation_angle_mrad": -0.019252940068347213
    },
    "14549": {
        "target_position": -0.5,
        "rotated_mean_x": 0.17543869813532736,
        "rotated_mean_y": 0.08122636215142291,
        "rotated_sigma_x": 0.2955959045289395,
        "rotated_sigma_y": 0.05668242360000138,
        "rotation_angle_mrad": -0.019599054535590837
    },
    "14550": {
        "target_position": -0.5,
        "rotated_mean_x": 0.1651962558467425,
        "rotated_mean_y": 0.08281140590067458,
        "rotated_sigma_x": 0.3003485248016224,
        "rotated_sigma_y": 0.05867940815585599,
        "rotation_angle_mrad": -0.02512054548626674
    },
    "14552": {
        "target_position": -0.5,
        "rotated_mean_x": 0.1773989608018827,
        "rotated_mean_y": 0.07966539643977216,
        "rotated_sigma_x": 0.30445644565209684,
        "rotated_sigma_y": 0.05801386055253746,
        "rotation_angle_mrad": -0.02193452179446375
    },
    "14556": {
        "target_position": -0.5,
        "rotated_mean_x": 0.1814031415045839,
        "rotated_mean_y": 0.08246024928267513,
        "rotated_sigma_x": 0.2987383477038409,
        "rotated_sigma_y": 0.05821796541133902,
        "rotation_angle_mrad": -0.02023390495429794
    },
    "14562": {
        "target_position": -0.5,
        "rotated_mean_x": 0.1780464922442497,
        "rotated_mean_y": 0.0793441762548789,
        "rotated_sigma_x": 0.29074521087073657,
        "rotated_sigma_y": 0.05085926592259831,
        "rotation_angle_mrad": -0.003196529381019576
    },
    "14563": {
        "target_position": -0.5,
        "rotated_mean_x": 0.19347188132215937,
        "rotated_mean_y": 0.09585398009976434,
        "rotated_sigma_x": 0.2945439442822664,
        "rotated_sigma_y": 0.05208253169335472,
        "rotation_angle_mrad": -0.007988810318959278
    },
    "14566": {
        "target_position": -0.5,
        "rotated_mean_x": 0.18773447593366205,
        "rotated_mean_y": 0.08557312631516487,
        "rotated_sigma_x": 0.30213970072433477,
        "rotated_sigma_y": 0.05262490631616312,
        "rotation_angle_mrad": -0.0030142163653105567
    },
    "14567": {
        "target_position": -0.5,
        "rotated_mean_x": 0.18994984177413635,
        "rotated_mean_y": 0.08805501936516315,
        "rotated_sigma_x": 0.3009819354587,
        "rotated_sigma_y": 0.053143354132246176,
        "rotation_angle_mrad": -0.004097401109971693
    },
    "14568": {
        "target_position": -0.5,
        "rotated_mean_x": 0.1924368813564613,
        "rotated_mean_y": 0.08656548735826813,
        "rotated_sigma_x": 0.29890017555626747,
        "rotated_sigma_y": 0.05292122304777731,
        "rotation_angle_mrad": -0.006710568968319981
    },
    "14569": {
        "target_position": -0.5,
        "rotated_mean_x": 0.18321864514906194,
        "rotated_mean_y": 0.09304395944708632,
        "rotated_sigma_x": 0.30168821832156495,
        "rotated_sigma_y": 0.05383619691287373,
        "rotation_angle_mrad": -0.006746557914455049
    },
    "14570": {
        "target_position": -0.5,
        "rotated_mean_x": 0.1866284267970759,
        "rotated_mean_y": 0.09024297818541613,
        "rotated_sigma_x": 0.3023413384278903,
        "rotated_sigma_y": 0.05394563912443496,
        "rotation_angle_mrad": -0.0072724536323222795
    },
    "14571": {
        "target_position": -0.5,
        "rotated_mean_x": 0.20209702290361586,
        "rotated_mean_y": 0.10421057571651127,
        "rotated_sigma_x": 0.29863346115620043,
        "rotated_sigma_y": 0.05314868147752894,
        "rotation_angle_mrad": -0.005662947786360506
    },
    "14572": {
        "target_position": -0.5,
        "rotated_mean_x": 0.16999292402927693,
        "rotated_mean_y": 0.0899527448287264,
        "rotated_sigma_x": 0.2961416342484748,
        "rotated_sigma_y": 0.05272437241026894,
        "rotation_angle_mrad": -0.003043533557409018
    },
    "14573": {
        "target_position": -0.5,
        "rotated_mean_x": 0.2326778468436164,
        "rotated_mean_y": 0.10396788966925553,
        "rotated_sigma_x": 0.2952671098653692,
        "rotated_sigma_y": 0.050786121605278685,
        "rotation_angle_mrad": -0.0008891203850380629
    },
    "14574": {
        "target_position": -0.5,
        "rotated_mean_x": 0.1884528949158715,
        "rotated_mean_y": 0.09111306387251145,
        "rotated_sigma_x": 0.30494276389462066,
        "rotated_sigma_y": 0.053283976089288455,
        "rotation_angle_mrad": -0.0015246856552918226
    },
    "14577": {
        "target_position": -0.5,
        "rotated_mean_x": 0.19404141343474746,
        "rotated_mean_y": 0.07797831409159625,
        "rotated_sigma_x": 0.3223250049340152,
        "rotated_sigma_y": 0.055701075087968205,
        "rotation_angle_mrad": -0.01597608481829344
    },
    "14578": {
        "target_position": -0.5,
        "rotated_mean_x": 0.1311682614524105,
        "rotated_mean_y": 0.08118801209723883,
        "rotated_sigma_x": 0.31066274997771,
        "rotated_sigma_y": 0.05547885939190605,
        "rotation_angle_mrad": -0.013060613209831628
    },
    "14579": {
        "target_position": -0.5,
        "rotated_mean_x": 0.1815917158128552,
        "rotated_mean_y": 0.08451791314961317,
        "rotated_sigma_x": 0.31573591906457804,
        "rotated_sigma_y": 0.05544886092436309,
        "rotation_angle_mrad": -0.01972201538491722
    },
    "14582": {
        "target_position": -0.5,
        "rotated_mean_x": 0.18452324570217268,
        "rotated_mean_y": 0.08566530567745174,
        "rotated_sigma_x": 0.3011345948411049,
        "rotated_sigma_y": 0.05321348089764385,
        "rotation_angle_mrad": -0.004883811389326743
    },
    "14583": {
        "target_position": -0.5,
        "rotated_mean_x": 0.19619571986702192,
        "rotated_mean_y": 0.0892564502677486,
        "rotated_sigma_x": 0.2996215424264057,
        "rotated_sigma_y": 0.052632954983068865,
        "rotation_angle_mrad": -0.00810218760478144
    },
    "14584": {
        "target_position": -0.5,
        "rotated_mean_x": 0.2137195354574336,
        "rotated_mean_y": 0.08307354487163139,
        "rotated_sigma_x": 0.30135185978819523,
        "rotated_sigma_y": 0.053561218138446054,
        "rotation_angle_mrad": -0.00791998367712788
    },
    "14585": {
        "target_position": -0.5,
        "rotated_mean_x": 0.2291059620155257,
        "rotated_mean_y": 0.11587860975889673,
        "rotated_sigma_x": 0.25877481628989996,
        "rotated_sigma_y": 0.04829134773919192,
        "rotation_angle_mrad": -0.0037230859835796623
    },
    "14594": {
        "target_position": -0.5,
        "rotated_mean_x": 0.1845303958079274,
        "rotated_mean_y": 0.09949013278452618,
        "rotated_sigma_x": 0.30993533387489497,
        "rotated_sigma_y": 0.04654232827759162,
        "rotation_angle_mrad": -0.004030870988876487
    },
    "14596": {
        "target_position": -0.5,
        "rotated_mean_x": 0.17663872138051023,
        "rotated_mean_y": 0.09481999600303465,
        "rotated_sigma_x": 0.3130051026186293,
        "rotated_sigma_y": 0.048977442858896804,
        "rotation_angle_mrad": -0.01003979303023793
    },
    "14597": {
        "target_position": -0.5,
        "rotated_mean_x": 0.17260744169613507,
        "rotated_mean_y": 0.09562164155501617,
        "rotated_sigma_x": 0.32282146452268645,
        "rotated_sigma_y": 0.05011510533987301,
        "rotation_angle_mrad": -0.012370784121343726
    },
    "14598": {
        "target_position": -0.5,
        "rotated_mean_x": 0.15424101362975584,
        "rotated_mean_y": 0.10075373095700126,
        "rotated_sigma_x": 0.28979131884167875,
        "rotated_sigma_y": 0.04620519589111676,
        "rotation_angle_mrad": -0.004183051188661832
    },
    "14600": {
        "target_position": -0.5,
        "rotated_mean_x": 0.1649491170570659,
        "rotated_mean_y": 0.09988453316209261,
        "rotated_sigma_x": 0.3116371400067652,
        "rotated_sigma_y": 0.05060547418666242,
        "rotation_angle_mrad": -0.002020277612830599
    },
    "14604": {
        "target_position": -0.5,
        "rotated_mean_x": 0.17830246349670464,
        "rotated_mean_y": 0.08742649874589985,
        "rotated_sigma_x": 0.3021060679608224,
        "rotated_sigma_y": 0.05262747368567387,
        "rotation_angle_mrad": -0.01588106183528052
    },
    "14608": {
        "target_position": -0.5,
        "rotated_mean_x": 0.20896418737676498,
        "rotated_mean_y": 0.09193332477226693,
        "rotated_sigma_x": 0.3210740413764132,
        "rotated_sigma_y": 0.05529168653217905,
        "rotation_angle_mrad": -0.024877998899865725
    },
    "14609": {
        "target_position": -0.5,
        "rotated_mean_x": 0.20685885960936568,
        "rotated_mean_y": 0.08939145627903222,
        "rotated_sigma_x": 0.32007319449688976,
        "rotated_sigma_y": 0.05533840001983689,
        "rotation_angle_mrad": -0.024160362722112323
    },
    "14610": {
        "target_position": -0.5,
        "rotated_mean_x": 0.21079417643684403,
        "rotated_mean_y": 0.08385861163721055,
        "rotated_sigma_x": 0.31980973764145715,
        "rotated_sigma_y": 0.05555139432072643,
        "rotation_angle_mrad": -0.02876156495082652
    },
    "14611": {
        "target_position": -0.5,
        "rotated_mean_x": 0.21048134623813294,
        "rotated_mean_y": 0.07304691130246438,
        "rotated_sigma_x": 0.3239664285218185,
        "rotated_sigma_y": 0.056710405082882456,
        "rotation_angle_mrad": -0.03403820487088428
    },
    "14612": {
        "target_position": -0.5,
        "rotated_mean_x": 0.2152521780933327,
        "rotated_mean_y": 0.06891794862777163,
        "rotated_sigma_x": 0.33317700970874636,
        "rotated_sigma_y": 0.05863173516695292,
        "rotation_angle_mrad": -0.029433686668268923
    },
    "14613": {
        "target_position": -0.5,
        "rotated_mean_x": 0.21015688721846543,
        "rotated_mean_y": 0.07868926968267086,
        "rotated_sigma_x": 0.314446293765623,
        "rotated_sigma_y": 0.05844223389426526,
        "rotation_angle_mrad": -0.025400606996646334
    },
    "14615": {
        "target_position": -0.5,
        "rotated_mean_x": 0.21502491814706753,
        "rotated_mean_y": 0.07676059766241895,
        "rotated_sigma_x": 0.31639965470232023,
        "rotated_sigma_y": 0.06038964470759842,
        "rotation_angle_mrad": -0.033690099665250134
    },
    "14616": {
        "target_position": -0.5,
        "rotated_mean_x": 0.19856816753846432,
        "rotated_mean_y": 0.08844302672703779,
        "rotated_sigma_x": 0.30719437378503694,
        "rotated_sigma_y": 0.060896684606732934,
        "rotation_angle_mrad": -0.032051919268151624
    },
    "14618": {
        "target_position": -0.5,
        "rotated_mean_x": 0.20424976685602256,
        "rotated_mean_y": 0.0817644872530023,
        "rotated_sigma_x": 0.3046273587511385,
        "rotated_sigma_y": 0.05995160791441509,
        "rotation_angle_mrad": -0.03294256866401391
    },
    "14619": {
        "target_position": -0.5,
        "rotated_mean_x": 0.19091536255347955,
        "rotated_mean_y": 0.0958820597658341,
        "rotated_sigma_x": 0.3063144721932563,
        "rotated_sigma_y": 0.05936673187000561,
        "rotation_angle_mrad": -0.028144494031167627
    },
    "14621": {
        "target_position": -0.5,
        "rotated_mean_x": 0.2051994395391303,
        "rotated_mean_y": 0.09157130672878552,
        "rotated_sigma_x": 0.3082922893144434,
        "rotated_sigma_y": 0.05935617999105722,
        "rotation_angle_mrad": -0.026879007832957703
    },
    "14685": {
        "target_position": -0.5,
        "rotated_mean_x": 0.08071401817846761,
        "rotated_mean_y": 0.06791352396986314,
        "rotated_sigma_x": 0.31875073548520366,
        "rotated_sigma_y": 0.057419045000175396,
        "rotation_angle_mrad": -0.03459563553123223
    },
    "14688": {
        "target_position": -0.5,
        "rotated_mean_x": 0.05593458175231968,
        "rotated_mean_y": 0.07328192765660753,
        "rotated_sigma_x": 0.31081392403069885,
        "rotated_sigma_y": 0.05910805978249417,
        "rotation_angle_mrad": -0.035783687819118844
    },
    "14689": {
        "target_position": -0.5,
        "rotated_mean_x": 0.08552603357451802,
        "rotated_mean_y": 0.07158409260071803,
        "rotated_sigma_x": 0.30936828847550757,
        "rotated_sigma_y": 0.05868782291905557,
        "rotation_angle_mrad": -0.03675119097715987
    },
    "14690": {
        "target_position": -0.5,
        "rotated_mean_x": 0.09090953865326065,
        "rotated_mean_y": 0.06918340504857073,
        "rotated_sigma_x": 0.3079105079540727,
        "rotated_sigma_y": 0.058845232646976296,
        "rotation_angle_mrad": -0.035614108158415154
    },
    "14691": {
        "target_position": -0.5,
        "rotated_mean_x": 0.05712863418804209,
        "rotated_mean_y": 0.07334807240866947,
        "rotated_sigma_x": 0.308213262684105,
        "rotated_sigma_y": 0.05863532932689453,
        "rotation_angle_mrad": -0.030321050563583696
    },
    "14693": {
        "target_position": -0.5,
        "rotated_mean_x": 0.06308140577195881,
        "rotated_mean_y": 0.06510838518248009,
        "rotated_sigma_x": 0.3082244753461469,
        "rotated_sigma_y": 0.05829303969813828,
        "rotation_angle_mrad": -0.02875271718339083
    },
    "14694": {
        "target_position": -0.5,
        "rotated_mean_x": 0.07006544476527583,
        "rotated_mean_y": 0.07686870664912222,
        "rotated_sigma_x": 0.3023701306726582,
        "rotated_sigma_y": 0.05602301797946218,
        "rotation_angle_mrad": -0.025881044713606464
    },
    "14696": {
        "target_position": -0.5,
        "rotated_mean_x": 0.0675013746680451,
        "rotated_mean_y": 0.06802265358700728,
        "rotated_sigma_x": 0.3039951565256001,
        "rotated_sigma_y": 0.05603338721422448,
        "rotation_angle_mrad": -0.027978895797850848
    },
    "14697": {
        "target_position": -0.5,
        "rotated_mean_x": 0.06740411444605808,
        "rotated_mean_y": 0.06761521105074554,
        "rotated_sigma_x": 0.3022995111228601,
        "rotated_sigma_y": 0.05727744249464987,
        "rotation_angle_mrad": -0.02920626588950678
    },
    "14699": {
        "target_position": -0.5,
        "rotated_mean_x": 0.0617147891159403,
        "rotated_mean_y": 0.07049103756848597,
        "rotated_sigma_x": 0.31025720939526996,
        "rotated_sigma_y": 0.05825777274022557,
        "rotation_angle_mrad": -0.02721953054617106
    },
    "14700": {
        "target_position": -0.5,
        "rotated_mean_x": 0.0717281241790752,
        "rotated_mean_y": 0.06725503964933553,
        "rotated_sigma_x": 0.31496151306370124,
        "rotated_sigma_y": 0.05845505665110076,
        "rotation_angle_mrad": -0.028275603303838145
    },
    "14701": {
        "target_position": -0.5,
        "rotated_mean_x": 0.06325600131390685,
        "rotated_mean_y": 0.06261973574622662,
        "rotated_sigma_x": 0.3082790342004889,
        "rotated_sigma_y": 0.05842353365736849,
        "rotation_angle_mrad": -0.025488065364148518
    },
    "14702": {
        "target_position": -0.5,
        "rotated_mean_x": 0.054823318583657174,
        "rotated_mean_y": 0.06351219955209009,
        "rotated_sigma_x": 0.3068634986111029,
        "rotated_sigma_y": 0.05854809341912335,
        "rotation_angle_mrad": -0.026516325461121648
    },
    "14706": {
        "target_position": -0.5,
        "rotated_mean_x": 0.07013924454515427,
        "rotated_mean_y": 0.06104717504698787,
        "rotated_sigma_x": 0.31024319900210484,
        "rotated_sigma_y": 0.05846521448465145,
        "rotation_angle_mrad": -0.02795717001763356
    },
    "14707": {
        "target_position": -0.5,
        "rotated_mean_x": 0.04716373876088408,
        "rotated_mean_y": 0.06462979656820526,
        "rotated_sigma_x": 0.30453745781512714,
        "rotated_sigma_y": 0.058682966781113094,
        "rotation_angle_mrad": -0.029441917379082777
    },
    "14708": {
        "target_position": -0.5,
        "rotated_mean_x": 0.07362315838114829,
        "rotated_mean_y": 0.06269452625322969,
        "rotated_sigma_x": 0.308132835836961,
        "rotated_sigma_y": 0.05983505763234859,
        "rotation_angle_mrad": -0.02676089125117639
    },
    "14709": {
        "target_position": -0.5,
        "rotated_mean_x": 0.07991033846037578,
        "rotated_mean_y": 0.065837766000178,
        "rotated_sigma_x": 0.31111173116398977,
        "rotated_sigma_y": 0.059089879807823056,
        "rotation_angle_mrad": -0.029195136814207347
    },
    "14710": {
        "target_position": -0.5,
        "rotated_mean_x": 0.08667799202082965,
        "rotated_mean_y": 0.06580193834132829,
        "rotated_sigma_x": 0.3101517145804623,
        "rotated_sigma_y": 0.0609297101822323,
        "rotation_angle_mrad": -0.0287645382064378
    },
    "14712": {
        "target_position": -0.5,
        "rotated_mean_x": 0.07267758208770667,
        "rotated_mean_y": 0.05984245267691124,
        "rotated_sigma_x": 0.3050110395623094,
        "rotated_sigma_y": 0.058678291742388325,
        "rotation_angle_mrad": -0.02398011885488085
    },
    "14713": {
        "target_position": -0.5,
        "rotated_mean_x": 0.06663963822878136,
        "rotated_mean_y": 0.061115449410929085,
        "rotated_sigma_x": 0.3048144971497243,
        "rotated_sigma_y": 0.05921223943245899,
        "rotation_angle_mrad": -0.026540969406134648
    },
    "14714": {
        "target_position": -0.5,
        "rotated_mean_x": 0.06692959408917919,
        "rotated_mean_y": 0.05707307976257438,
        "rotated_sigma_x": 0.3050888920029222,
        "rotated_sigma_y": 0.05971051525036699,
        "rotation_angle_mrad": -0.028672434086777214
    },
    "14715": {
        "target_position": -0.5,
        "rotated_mean_x": 0.07524887618541125,
        "rotated_mean_y": 0.05437249411176383,
        "rotated_sigma_x": 0.3118395323400062,
        "rotated_sigma_y": 0.06071399569063422,
        "rotation_angle_mrad": -0.029400663170099168
    },
    "14716": {
        "target_position": -0.5,
        "rotated_mean_x": 0.07950267307548088,
        "rotated_mean_y": 0.06046714450540798,
        "rotated_sigma_x": 0.3167422266883952,
        "rotated_sigma_y": 0.06256919020603502,
        "rotation_angle_mrad": -0.03145422587451744
    },
    "14718": {
        "target_position": -0.5,
        "rotated_mean_x": 0.07571719113821687,
        "rotated_mean_y": 0.060229067941960784,
        "rotated_sigma_x": 0.3088128539346449,
        "rotated_sigma_y": 0.06053359093379645,
        "rotation_angle_mrad": -0.028617619971690093
    },
    "14719": {
        "target_position": -0.5,
        "rotated_mean_x": 0.06826876132908011,
        "rotated_mean_y": 0.06314934231178694,
        "rotated_sigma_x": 0.30754428081103014,
        "rotated_sigma_y": 0.06214217563602922,
        "rotation_angle_mrad": -0.029607596448010753
    },
    "14720": {
        "target_position": -0.5,
        "rotated_mean_x": 0.07398340147904207,
        "rotated_mean_y": 0.062046815427956696,
        "rotated_sigma_x": 0.31265149369595,
        "rotated_sigma_y": 0.0617599340390754,
        "rotation_angle_mrad": -0.025380804519744136
    },
    "14721": {
        "target_position": -0.5,
        "rotated_mean_x": 0.11145172613213163,
        "rotated_mean_y": 0.06078985223670346,
        "rotated_sigma_x": 0.31098582395574415,
        "rotated_sigma_y": 0.0612802664015954,
        "rotation_angle_mrad": -0.02721120306166126
    },
    "14722": {
        "target_position": -0.5,
        "rotated_mean_x": 0.06699526913011186,
        "rotated_mean_y": 0.062299957552122205,
        "rotated_sigma_x": 0.3132505080993202,
        "rotated_sigma_y": 0.06212027222935758,
        "rotation_angle_mrad": -0.028973341339530733
    },
    "14726": {
        "target_position": -0.5,
        "rotated_mean_x": 0.07739618690876744,
        "rotated_mean_y": 0.057744368723755955,
        "rotated_sigma_x": 0.3118163359120178,
        "rotated_sigma_y": 0.05989297431657239,
        "rotation_angle_mrad": -0.02815719168014864
    },
    "14727": {
        "target_position": -0.5,
        "rotated_mean_x": 0.06926704733961193,
        "rotated_mean_y": 0.05764804696843423,
        "rotated_sigma_x": 0.3103120541938733,
        "rotated_sigma_y": 0.059676126882835745,
        "rotation_angle_mrad": -0.029261760802322876
    },
    "14728": {
        "target_position": -0.5,
        "rotated_mean_x": 0.0704369328816975,
        "rotated_mean_y": 0.05915313665198502,
        "rotated_sigma_x": 0.31314102766058194,
        "rotated_sigma_y": 0.0668154585199012,
        "rotation_angle_mrad": -0.0334174804468498
    },
    "14729": {
        "target_position": -0.5,
        "rotated_mean_x": 0.07352039545606899,
        "rotated_mean_y": 0.0617325233897424,
        "rotated_sigma_x": 0.31380786774944175,
        "rotated_sigma_y": 0.06632351351803054,
        "rotation_angle_mrad": -0.034365006565686675
    },
    "14730": {
        "target_position": -0.5,
        "rotated_mean_x": 0.07439898506502561,
        "rotated_mean_y": 0.06148968680608129,
        "rotated_sigma_x": 0.31222794966306455,
        "rotated_sigma_y": 0.06673563834891648,
        "rotation_angle_mrad": -0.030453844588960437
    },
    "14731": {
        "target_position": -0.5,
        "rotated_mean_x": 0.0730242190942777,
        "rotated_mean_y": 0.05862887749309521,
        "rotated_sigma_x": 0.3147543339327969,
        "rotated_sigma_y": 0.06685523119142356,
        "rotation_angle_mrad": -0.030323405674485746
    },
    "14732": {
        "target_position": -0.5,
        "rotated_mean_x": 0.08218108094436825,
        "rotated_mean_y": 0.055951128590006664,
        "rotated_sigma_x": 0.3304845552319972,
        "rotated_sigma_y": 0.06722412934293501,
        "rotation_angle_mrad": -0.036959484726181026
    },
    "14734": {
        "target_position": -0.5,
        "rotated_mean_x": 0.060125893220449915,
        "rotated_mean_y": 0.057641990585323676,
        "rotated_sigma_x": 0.31104024753252946,
        "rotated_sigma_y": 0.06544918365147549,
        "rotation_angle_mrad": -0.03413796526559244
    },
    "14736": {
        "target_position": -0.5,
        "rotated_mean_x": 0.053264709584977504,
        "rotated_mean_y": 0.05702936889188133,
        "rotated_sigma_x": 0.31043026146886915,
        "rotated_sigma_y": 0.06265617546175166,
        "rotation_angle_mrad": -0.03391497391247106
    },
    "14737": {
        "target_position": -0.5,
        "rotated_mean_x": 0.0669385788399696,
        "rotated_mean_y": 0.06042759198361721,
        "rotated_sigma_x": 0.314070120510048,
        "rotated_sigma_y": 0.06137715403009021,
        "rotation_angle_mrad": -0.02886509332236988
    },
    "14738": {
        "target_position": -0.5,
        "rotated_mean_x": 0.036174735488309046,
        "rotated_mean_y": 0.05604851046634794,
        "rotated_sigma_x": 0.31736483046412467,
        "rotated_sigma_y": 0.061322385500774186,
        "rotation_angle_mrad": -0.029323621103398888
    },
    "14739": {
        "target_position": -0.5,
        "rotated_mean_x": 0.08202056087188868,
        "rotated_mean_y": 0.05710832787588201,
        "rotated_sigma_x": 0.31117335582295885,
        "rotated_sigma_y": 0.060639210365432884,
        "rotation_angle_mrad": -0.028045192509065803
    },
    "14741": {
        "target_position": -0.5,
        "rotated_mean_x": 0.06429794381707175,
        "rotated_mean_y": 0.05139540082014969,
        "rotated_sigma_x": 0.3157849205478751,
        "rotated_sigma_y": 0.061488080747249506,
        "rotation_angle_mrad": -0.028789145583154225
    },
    "14742": {
        "target_position": -0.5,
        "rotated_mean_x": 0.05485278934060614,
        "rotated_mean_y": 0.052298360748164636,
        "rotated_sigma_x": 0.31009806511507987,
        "rotated_sigma_y": 0.06118225517938117,
        "rotation_angle_mrad": -0.03216720862000152
    },
    "14744": {
        "target_position": -0.5,
        "rotated_mean_x": 0.0483679411589621,
        "rotated_mean_y": 0.05380734957016542,
        "rotated_sigma_x": 0.3163172924501431,
        "rotated_sigma_y": 0.06240157888558384,
        "rotation_angle_mrad": -0.030944859032817344
    },
    "14745": {
        "target_position": -0.5,
        "rotated_mean_x": 0.037182895414673546,
        "rotated_mean_y": 0.05313095899973069,
        "rotated_sigma_x": 0.31473000665726963,
        "rotated_sigma_y": 0.06327432167336319,
        "rotation_angle_mrad": -0.03307500521825464
    },
    "14746": {
        "target_position": -0.5,
        "rotated_mean_x": 0.06037168876877251,
        "rotated_mean_y": 0.06106121851822435,
        "rotated_sigma_x": 0.3162572899847475,
        "rotated_sigma_y": 0.06343629748394829,
        "rotation_angle_mrad": -0.035712715369164635
    },
    "14747": {
        "target_position": -0.5,
        "rotated_mean_x": 0.05679555269410575,
        "rotated_mean_y": 0.05718096578057247,
        "rotated_sigma_x": 0.3388929907307416,
        "rotated_sigma_y": 0.06359521045137605,
        "rotation_angle_mrad": -0.036666452187415766
    },
    "14748": {
        "target_position": -0.5,
        "rotated_mean_x": 0.03601251940052368,
        "rotated_mean_y": 0.04910984365046728,
        "rotated_sigma_x": 0.34110717956099573,
        "rotated_sigma_y": 0.06219305887838829,
        "rotation_angle_mrad": -0.034458730386504065
    },
    "14749": {
        "target_position": -0.5,
        "rotated_mean_x": 0.047394492362199975,
        "rotated_mean_y": 0.059958430769566064,
        "rotated_sigma_x": 0.34544985058742506,
        "rotated_sigma_y": 0.06240474271359224,
        "rotation_angle_mrad": -0.03143036782313328
    },
    "14750": {
        "target_position": -0.5,
        "rotated_mean_x": 0.0396022939888415,
        "rotated_mean_y": 0.05645259178964598,
        "rotated_sigma_x": 0.3361332409107647,
        "rotated_sigma_y": 0.06245695344442145,
        "rotation_angle_mrad": -0.03203024624135665
    },
    "14751": {
        "target_position": -0.5,
        "rotated_mean_x": 0.025286102361424496,
        "rotated_mean_y": 0.05042706104881813,
        "rotated_sigma_x": 0.3333886388967528,
        "rotated_sigma_y": 0.061458666231736105,
        "rotation_angle_mrad": -0.030788769185692955
    },
    "14756": {
        "target_position": -0.5,
        "rotated_mean_x": 0.044141631688756296,
        "rotated_mean_y": 0.062126449691874246,
        "rotated_sigma_x": 0.3449327575032473,
        "rotated_sigma_y": 0.06285334410520203,
        "rotation_angle_mrad": -0.03802803124184721
    }
}
